{
  "$schema": "../gen/schemas/desktop-schema.json",
  "identifier": "default",
  "description": "enables the default permissions",
  "windows": [
    "main"
  ],
  "permissions": [
    "core:default",
    "core:window:default",
    "core:window:allow-minimize",
    "core:window:allow-maximize",
    "core:window:allow-destroy",
    "core:window:allow-unmaximize",
    "fs:allow-applocaldata-meta",
    "fs:allow-localdata-meta-recursive",
    "fs:scope-localdata",
    "fs:scope-localdata-recursive",
    "fs:allow-localdata-write",
    "fs:allow-localdata-read",
    "fs:read-all",
    "fs:allow-localdata-read-recursive",
    "fs:allow-read",
    "system-info:allow-all",
    "system-info:allow-batteries",
    "websocket:default",
    "websocket:allow-connect",
    "websocket:allow-send",
    "dialog:default",
    "fs:default",
    "prevent-default:default",
    "shell:default"
  ]
}